{
  "_note": "HSV color ranges for team kit identification. H: 0-179, S: 0-255, V: 0-255. Each team has primary (home) kit colors.",
  "AC Milan": {"primary": {"h_range": [0, 30], "s_min": 80, "v_min": 60, "label": "red/black"}},
  "Antwerp": {"primary": {"h_range": [0, 30], "s_min": 80, "v_min": 60, "label": "red"}},
  "Arsenal": {"primary": {"h_range": [0, 30], "s_min": 80, "v_min": 80, "label": "red"}},
  "Aston Villa": {"primary": {"h_range": [130, 160], "s_min": 40, "v_min": 40, "label": "claret"}},
  "Atalanta": {"primary": {"h_range": [100, 130], "s_min": 80, "v_min": 60, "label": "blue/black"}},
  "Atletico Madrid": {"primary": {"h_range": [0, 30], "s_min": 80, "v_min": 80, "label": "red/white stripes"}},
  "Barcelona": {"primary": {"h_range": [100, 130], "s_min": 80, "v_min": 60, "label": "blue/red"}},
  "Bayer Leverkusen": {"primary": {"h_range": [0, 30], "s_min": 80, "v_min": 60, "label": "red/black"}},
  "Bayern Munich": {"primary": {"h_range": [0, 30], "s_min": 80, "v_min": 80, "label": "red"}},
  "Benfica": {"primary": {"h_range": [0, 30], "s_min": 80, "v_min": 80, "label": "red"}},
  "Bologna": {"primary": {"h_range": [0, 30], "s_min": 80, "v_min": 60, "label": "red/blue"}},
  "Braga": {"primary": {"h_range": [0, 30], "s_min": 80, "v_min": 60, "label": "red"}},
  "Brest": {"primary": {"h_range": [0, 179], "s_min": 0, "v_min": 200, "label": "white"}},
  "Celtic": {"primary": {"h_range": [35, 85], "s_min": 80, "v_min": 60, "label": "green/white"}},
  "Club Brugge": {"primary": {"h_range": [100, 130], "s_min": 80, "v_min": 60, "label": "blue/black"}},
  "Crvena Zvezda": {"primary": {"h_range": [0, 30], "s_min": 80, "v_min": 80, "label": "red/white"}},
  "Dinamo Zagreb": {"primary": {"h_range": [100, 130], "s_min": 80, "v_min": 100, "label": "blue"}},
  "Dortmund": {"primary": {"h_range": [20, 35], "s_min": 150, "v_min": 150, "label": "yellow"}},
  "FC Copenhagen": {"primary": {"h_range": [0, 179], "s_min": 0, "v_min": 200, "label": "white"}},
  "Feyenoord": {"primary": {"h_range": [0, 30], "s_min": 80, "v_min": 60, "label": "red/white"}},
  "Galatasaray": {"primary": {"h_range": [5, 30], "s_min": 100, "v_min": 100, "label": "orange/red"}},
  "Girona": {"primary": {"h_range": [0, 30], "s_min": 80, "v_min": 60, "label": "red/white"}},
  "Inter Milan": {"primary": {"h_range": [100, 130], "s_min": 80, "v_min": 60, "label": "blue/black"}},
  "Juventus": {"primary": {"h_range": [0, 179], "s_min": 0, "v_min": 180, "label": "white/black"}},
  "Lazio": {"primary": {"h_range": [90, 120], "s_min": 60, "v_min": 150, "label": "light blue"}},
  "Lens": {"primary": {"h_range": [5, 20], "s_min": 150, "v_min": 150, "label": "orange/gold"}},
  "Lille": {"primary": {"h_range": [0, 30], "s_min": 80, "v_min": 60, "label": "red"}},
  "Liverpool": {"primary": {"h_range": [0, 30], "s_min": 80, "v_min": 80, "label": "red"}},
  "Man City": {"primary": {"h_range": [90, 110], "s_min": 60, "v_min": 150, "label": "sky blue"}},
  "Manchester United": {"primary": {"h_range": [0, 30], "s_min": 80, "v_min": 80, "label": "red"}},
  "Monaco": {"primary": {"h_range": [0, 30], "s_min": 80, "v_min": 80, "label": "red/white"}},
  "Napoli": {"primary": {"h_range": [90, 115], "s_min": 80, "v_min": 120, "label": "sky blue"}},
  "Newcastle": {"primary": {"h_range": [0, 179], "s_min": 0, "v_min": 0, "label": "black/white stripes"}},
  "PSG": {"primary": {"h_range": [100, 130], "s_min": 80, "v_min": 60, "label": "dark blue"}},
  "PSV": {"primary": {"h_range": [0, 30], "s_min": 80, "v_min": 60, "label": "red/white"}},
  "Porto": {"primary": {"h_range": [100, 130], "s_min": 80, "v_min": 100, "label": "blue/white"}},
  "RB Leipzig": {"primary": {"h_range": [0, 179], "s_min": 0, "v_min": 200, "label": "white"}},
  "Real Madrid": {"primary": {"h_range": [0, 179], "s_min": 0, "v_min": 200, "label": "white"}},
  "Real Sociedad": {"primary": {"h_range": [100, 130], "s_min": 60, "v_min": 100, "label": "blue/white"}},
  "Red Star Belgrade": {"primary": {"h_range": [0, 30], "s_min": 80, "v_min": 80, "label": "red/white"}},
  "Salzburg": {"primary": {"h_range": [0, 179], "s_min": 0, "v_min": 200, "label": "white"}},
  "Sevilla": {"primary": {"h_range": [0, 179], "s_min": 0, "v_min": 200, "label": "white"}},
  "Shakhtar Donetsk": {"primary": {"h_range": [10, 25], "s_min": 150, "v_min": 150, "label": "orange"}},
  "Slovan Bratislava": {"primary": {"h_range": [90, 120], "s_min": 60, "v_min": 120, "label": "light blue"}},
  "Sparta Prague": {"primary": {"h_range": [0, 30], "s_min": 60, "v_min": 40, "label": "dark red"}},
  "Sporting CP": {"primary": {"h_range": [35, 85], "s_min": 80, "v_min": 60, "label": "green/white"}},
  "Sturm Graz": {"primary": {"h_range": [0, 179], "s_min": 0, "v_min": 0, "label": "black/white"}},
  "Stuttgart": {"primary": {"h_range": [0, 179], "s_min": 0, "v_min": 200, "label": "white/red"}},
  "Union Berlin": {"primary": {"h_range": [0, 30], "s_min": 80, "v_min": 60, "label": "red/white"}},
  "Young Boys": {"primary": {"h_range": [20, 35], "s_min": 150, "v_min": 150, "label": "yellow"}}
}
